[
  {
    "name":"Husky Campus Run",
    "upcoming_date":"now",
    "upcoming_days": 0,
    "time":"10:00 AM",
    "location":"Husky Track",
    "img":"img/running.jpg",
    "detail":"Lorem ipsum dolor sit amet consectetur adipisicing elit. Hic quo voluptates sint laudantium quaerat commodi!"
  },
  {
    "name":"Pick-Up Basketball",
    "upcoming_date":"one week",
    "upcoming_days": 7,
    "time":"11:00 PM",
    "location":"IMA",
    "img":"img/basketBall.jpg",
    "detail":"Lorem ipsum dolor sit amet consectetur adipisicing elit. Hic quo voluptates sint laudantium quaerat commodi!"
  },
  {
    "name":"Tennis Games",
    "upcoming_date":"two weeks",
    "upcoming_days": 14,
    "time":"3:00 PM",
    "location":"IMA",
    "img":"img/tennis.webp",
    "detail":"Lorem ipsum dolor sit amet consectetur adipisicing elit. Hic quo voluptates sint laudantium quaerat commodi!"
  },
  {
    "name":"Huskies Football Game",
    "upcoming_date":"one month",
    "upcoming_days": 30,
    "time":"1:00 PM",
    "location":"IMA",
    "img":"img/football.jpg",
    "detail":"Lorem ipsum dolor sit amet consectetur adipisicing elit. Hic quo voluptates sint laudantium quaerat commodi!"
  }
]